---
title: "Hatena2011-02-07"
---

hatena

```
<body>
*1297067116*同じ値がN個入っているリストの作り方
Twitterより転載:
>>
atsuoishimoto: .@t2y http://htn.to/qWhHgD [0 for i in xrange(len(seqs))] みたいな書き方たまに見かけるけど、正解は [0]*len(seqs) だと思う。
<<

とても正しいツッコミだけど、若干不親切だと思うので勝手に補足。

たとえば「0がN個入っているリスト」を作るのは[0] * Nだ。

>|python|
>>> N = 5
>>> [0] * N
[0, 0, 0, 0, 0]
||<

この書き方は0に限らず「同じものがN個入ったリスト」を作ることに使える。

>|python|
>>> ['a'] * N
['a', 'a', 'a', 'a', 'a']
||<

じゃあ、「空のリストがN個入ったリスト」を作りたい場合は？うん、その場合ももちろん同じように書ける。
>|python|
>>> [[]] * N
[[], [], [], [], []]
||<

しかし、これが「同じ『空のリスト』がN個入ったリスト」であるということをきちんと理解しているかな？

>|python|
>>> lists = [[]] * N
>>> lists[0] # listsの0番目は空のリストだ
[]
>>> lists[0].append(1) # これに1を追加すると
>>> lists[0] # [1]に変わる。うん当たり前。
[1]
>>> lists # で、listsはどうなっている？
[[1], [1], [1], [1], [1]]
||<

listsは「同じ空リスト」が5つ入ったリストだったのだから当然こうなるわけである。でもまあ「リストのリスト」を作りたい時って普通はこういうことがしたいわけじゃないよね。「別々の空リスト」が5個入ったリストが欲しいんだよね。じゃあこうだ。

>|python|
>>> [[] for i in range(N)]
[[], [], [], [], []]
||<

これならば見かけは1つ目の方法で作ったリストと同じだけど、それぞれの空リストはそれぞれ別の空リストだ。

>|python|
>>> lists = [[] for i in range(N)]
>>> lists[0].append(1)
>>> lists
[[1], [], [], [], []]
||<

というわけで、例えば「要素が0の2次元配列を作りたい」という場合にはこうだ。

>|python|
>>> from pprint import pprint
>>> pprint([[0] * N for i in range(N)])
[[0, 0, 0, 0, 0],
 [0, 0, 0, 0, 0],
 [0, 0, 0, 0, 0],
 [0, 0, 0, 0, 0],
 [0, 0, 0, 0, 0]]
||<

多分最初に突っ込まれていた人は「同じ物」なのか「同じ値の別の物」なのかで使い分けが必要であることを理解していなかったのだろう。

*1297082406*デフォルト引数の評価タイミング
Twitterより転載
>>
shimizukawa: あるあるｗ あわせて覚えたい：関数引数のデフォルト値に arg=[] したときの挙動 RT @nishio: @atsuoishimoto 正しいけど不親切だと思ったので補足しました: 同じ値がN個入っているリストの作り方 http://bit.ly/eW2oaF
<<

はいはい、じゃあそれも書いておきましょう！

Pythonの長所の一つはdisでバイトコードが読めることだと思うので疑問に思ったらとりあえずみんなdisればいいとおもうよ！

>|python|
>>> import dis
>>> def bar():
...     def foo(x=1, y=2, z=[]):
...         pass
... 
>>> dis.dis(bar)
  2           0 LOAD_CONST               1 (1)
              3 LOAD_CONST               2 (2)
              6 BUILD_LIST               0
              9 LOAD_CONST               3 (<code object foo at 0x10046ccd8, file "<stdin>", line 2>)
             12 MAKE_FUNCTION            3
             15 STORE_FAST               0 (foo)
             18 LOAD_CONST               0 (None)
             21 RETURN_VALUE        
||<

不慣れな人のためにわかり易く説明を付けると:

>||
LOAD_CONST (1) # 1を用意して
LOAD_CONST (2) # 2を用意して
BUILD_LIST # リストを作って
LOAD_CONST (<code object>) # 関数の中身を用意して
MAKE_FUNCTION 3 # 3つの値をデフォルト引数につかって関数を作成
STORE_FAST (foo) # その関数にfooって名前をつけて
LOAD_CONST (None) # Noneを用意して
RETURN_VALUE # それを返す
||<

関数を定義する前にデフォルト値[]を作るBUILD_LISTが走っているのがわかる。っていうことはどういうことかというと、当然そのデフォルト値の実体は関数の実体と一対一なので下のような挙動が起きる。


>|python|
>>> def foo(x=[]):
...     x.append(1)
...     print x
... 
>>> foo()
[1]
>>> foo()
[1, 1]
||<

実用的な例で言えば、「引数で時刻を指定する関数があって、その引数を省略したら現在の時刻を使いたい」なんてケース。

>|python|
>>> from datetime import datetime
>>> def foo(when=datetime.now()):
...     print when
... 
>>> foo()
2011-02-07 20:42:43.578936 # 引数省略してもちゃんと動いた
>>> foo(datetime.now())
2011-02-07 20:42:51.446415 # 引数指定してもちゃんと動いた。
# よーしうまく動いているぞ、なんて思ったら…
>>> foo()
2011-02-07 20:42:43.578936 # 引数省略したときには同じ時刻が返ってくる…
||<

こういう場合の対処法は引数の省略時の値をNoneにしておいて「Noneの時には現在時刻」と書くことかと思う。

>|python|
>>> def foo(when=None):
...     if not when: when = datetime.now()
...     print when
... 
>>> foo()
2011-02-07 20:43:36.233154
>>> foo()
2011-02-07 20:43:37.539578 # ちゃんと動いている
||<
</body>
<comments>
<comment>
<username>ujihisa</username>
<body>http://ujihisa.blogspot.com/2009/06/default-parameter-dynamic-define.html<br><br>これを思い出しつつ、仮引数で再帰関数定義をpythonでもやってみましたが、<br><br><br>def fib(n, x = 0 if n == 0 else 1 if n == 1 else fib(n-2) + fib(n-1)):<br>  return x<br><br>print fib(10)<br><br><br>NameError: name 'n' is not defined<br>ざんねん</body>
<timestamp>1297125437</timestamp>
</comment>
</comments>
```


[はてなダイアリー 2011-02-07](https://nishiohirokazu.hatenadiary.org/archive/2011/02/07)