
hatena

```
<body>
*1301568313*printf("%d", f)でfがfloatの時の挙動について
型はバイト幅だけじゃなくてどうやって二進法でエンコードするのかも規定するよね、という話をしていて確認のためのコードを書いた。手抜きをして方法Bでやってもいいよね、と思ったら予想外の結果が出たので悩んでいる。→解決

>|cpp|
#include<stdio.h>
int main(){
  int i;
  float f = 1.0;
  /* 素直な方法 A (追記：やっちゃダメ！)*/
  i = *(int*)(&f);
  printf("A %d\n", i);
  /* 手抜きな方法 B */
  printf("B %d\n", f);
}
||<

Rubyでこんな感じに文字列化して、と。
>|ruby|
irb> def pp(x) x.to_s(2).rjust(32, "0") end
irb> pp 1065353216
=> "00111111100000000000000000000000"
||<

>||
0.500000の時
A 1056964608 : 00111111000000000000000000000000
B 8388608    : 00000000100000000000000000000000

1.000000の時
A 1065353216 : 00111111100000000000000000000000
B 8388608    : 00000000100000000000000000000000

2.000000の時
A 1073741824 : 01000000000000000000000000000000
B 8388608    : 00000000100000000000000000000000
||<

なんでBの方は値が変わらないのだろう？まあ方法Aを使えば問題ないんだけど、理由がわからないのはすっきりしないな。

<hr>
怒られる前に追記
>||
$ uname -a
Darwin nishio.local 10.7.0 Darwin Kernel Version 10.7.0: Sat Jan 29 15:17:16 PST 2011; root:xnu-1504.9.37~1/RELEASE_I386 i386

$ gcc -v
Using built-in specs.
Target: i686-apple-darwin10
Configured with: /var/tmp/gcc/gcc-5659~1/src/configure --disable-checking --enable-werror --prefix=/usr --mandir=/share/man --enable-languages=c,objc,c++,obj-c++ --program-transform-name=/^[cg][^.-]*$/s/$/-4.2/ --with-slibdir=/usr/lib --build=i686-apple-darwin10 --program-prefix=i686-apple-darwin10- --host=x86_64-apple-darwin10 --target=i686-apple-darwin10 --with-gxx-include-dir=/include/c++/4.2.1
Thread model: posix
gcc version 4.2.1 (Apple Inc. build 5659)
||<

<hr>
解決編
>>
nyaxt: 西尾さんのぶろぐよんだ。プラットフォームがx64じゃないかというえすぱー。
nyaxt: ABIじゃないかなーという。x86だと全部スタックにつむけど、x64だとレジスタ渡しするので浮動小数点数はmmxレジスタにはいるんじゃね(追記：以下s/MMX/SSE/ig)

nyaxt: やっぱりそうだw 手元のこーどみたらやっぱりBだとxmm0にmovssしてる

nishio_: MMXレジスタに入れて、そこからとってもらえるつもりで呼んだのに、printfの側が「%dだからスタックから取ろう」って取って変な値を返しているってこと？
nyaxt: スタックからとってるんじゃなくてレジスタからとってるはず
nishio_: 浮動小数点を渡そうと思ってMMXレジスタに入れたけど、printfは別のレジスタから取っちゃって値が変になる、ってことか
nyaxt: そうそう

nyaxt: これを応用するとこういう手品ができる
<pre>
#include<stdio.h>
int main(){
  printf("A: %d %f %d %f \n", 1, 2.0, 3, 4.0);
  printf("A: %d %f %d %f \n", 1, 3, 2.0, 4.0);
}
</pre>
nishio_: 面白い
nyaxt: 元ネタはshinhさんなので http://shinh.skr.jp/slide/tcc64/000.html
nishio_: 言及しとく
<<

<hr>
などと書いていたら解決編2
>>
@herumi: いや，それ素直な方法も手抜きな方法も未定義なコードですから何が起こっても文句言えないです．gccならC99の%aを使うのも手． http://linuxjm.sourceforge.jp/html/LDP_man-pages/man3/printf.3.html
<<

>>
@gusmachine: unionを使うのが正解、でしょうか? http://bit.ly/fUn8wb
<<
>|cpp|
#include<stdio.h>
union intfloat{
  int i;
  float f;
};

int main(){
  intfloat x;
  x.f = 1.0;
  printf("%f\n", x.f);
  printf("int %d\n", x.i); //-> 1065353216
}
||<

これが正解ですね。

<hr>

>>
@kosaki55tea 一般にはxmmはMMXレジスタとは言わない気がするのですが僕の周囲だけ？mm0とかがMMXレジスタでxmm0とかはSSEレジスタのような
<<
たしかにここでもSSEレジスタと書かれてますね: <a href='http://homepage1.nifty.com/herumi/prog/prog00.html'>about x86 CPU</a>

*1301581470*最小限VM
手元にWEB-DB Press vol.60の「言語設計の基礎知識」がある人はP.28を参照ください。ここにあるような「カウントダウンをするwhile」、原稿ではC言語で説明していますけど、本当は機械語とかにもふれたかったのですよ。紙面と時間の都合でできていないのですけど。
で、生の機械語はそれはそれで色々説明しないといけないから大変かな、と思ってwhileを実現するために最小限の仮想機械を作ってみました。

>|python|
# -*- encoding: utf-8 -*-
"""
mini-VM 解説のための最小限のVM
最小限とは？最小限である必要があるか？
チューリング完全である必要があるのか？

jump pos : PCをposに変更
if_eq a1 v1 pos : mem[a1] == v1 ならjump pos
print a1 : mem[a1]をprint
set a1 v1 : mem[a1]をv1にする
sub v1 : mem[0]からv1を引く
"""

memory = [0] * 10
code = [
    ("set", 0, 10), # A = 10
    ("if_eq", 0, 5), # 1: if A == 0
    ("sub", 1), # A = A - 1
    ("print", 0), # print A
    ("jump", 1),
]

def eval(code):
    cur = 0
    while cur < len(code):
        line = code[cur]
        cur += 1
        op = line[0]
        if op == "set":
            memory[line[1]] = line[2]
        elif op == "print":
            print memory[line[1]]
        elif op == "if_eq":
            if memory[0] == line[1]:
                cur = line[2]
        elif op == "sub":
            memory[0] -= line[1]
        elif op == "jump":
            cur = line[1]

eval(code)
||<

あとPythonのバイトコードではこんな感じ。真偽値をスタックに詰んでるところがちょっと違うか。
>||
>>> def foo():
...     x = 10
...     while x > 0:
...             print x
...             x -= 1
... 
>>> dis.dis(foo) # 必要ないところは削除
  2           0 LOAD_CONST               1 (10)
              3 STORE_FAST               0 (x)

  3           6 SETUP_LOOP              33 (to 42)
        >>    9 LOAD_FAST                0 (x)
             12 LOAD_CONST               2 (0)
             15 COMPARE_OP               4 (>)
             18 JUMP_IF_FALSE           19 (to 40)
             21 POP_TOP             

  4          22 LOAD_FAST                0 (x)
             25 PRINT_ITEM          
             26 PRINT_NEWLINE       

  5          27 LOAD_FAST                0 (x)
             30 LOAD_CONST               3 (1)
             33 INPLACE_SUBTRACT    
             34 STORE_FAST               0 (x)
             37 JUMP_ABSOLUTE            9
        >>   40 POP_TOP             
             41 POP_BLOCK           
||<

で、これでif, while, forまでは作れるわけなのだけども、関数をつくろうと思うと今の「飛び先固定のジャンプ」ではできない。そこでcallとreturnを作ろう、と思ったのだけど、そもそもこのVMでプログラムカウンタがコードからいじれるメモリー領域上にないのが行けないのであって、こういう管理に必要な値自身もmemに入れるべきだったのかもなぁ。

<hr>
Pythonで書いてディスアセンブルしたものを見せるんだったら別にネイティブでも良くない？と気づいたのでやってみた。

>|cpp|
#include<stdio.h>
int main(){
  __asm__("#set x value");
  int x = 10;
  __asm__("#start loop");
  while(x > 0){
    __asm__("#print x");
    printf("%d\n", x);
    __asm__("#decrement x");
    x--;
    __asm__("#end of loop body");
  }
  __asm__("#end of loop");
}
||<

>||
        #set x value
        movl    $10, -4(%rbp)
        #start loop
        jmp     L2
L3:
        #print x
        movl    -4(%rbp), %esi
        leaq    LC0(%rip), %rdi
        movl    $0, %eax
        call    _printf
        #decrement x
        decl    -4(%rbp)
        #end of loop body
L2:
        cmpl    $0, -4(%rbp)
        jg      L3
        #end of loop
||<

いきなり下に飛ぶのかー。ふむふむ。まあでもこれ説明をちゃんと書けば予備知識のない人でも読める気がする。
</body>
<comments>
<comment>
<username>kosaki</username>
<body>スタックにpushしてないんでは？fがfloating registerにあるのに、%dだからってgeneral purpose registerを見に行ってるとかそんな系統の</body>
<timestamp>1301569002</timestamp>
</comment>
</comments>
```


[はてなダイアリー 2011-03-31](https://nishiohirokazu.hatenadiary.org/archive/2011/03/31)